py_attire_schema/__init__.py
py_attire_schema/schemas.py
py_attire_schema-1.1.0.dist-info/LICENSE
py_attire_schema-1.1.0.dist-info/WHEEL
py_attire_schema-1.1.0.dist-info/METADATA
py_attire_schema-1.1.0.dist-info/RECORD
