Metadata-Version: 2.1
Name: py-attire-schema
Version: 1.1.0
Summary: Base logging schema used by attire logger projects
Home-page: https://github.com/SecurityRiskAdvisors/py-attire-schema
License: MIT
Author: jamesgeraghty
Requires-Python: >=3.6.1,<4.0.0
Classifier: License :: OSI Approved :: MIT License
Classifier: Programming Language :: Python :: 3
Classifier: Programming Language :: Python :: 3.10
Classifier: Programming Language :: Python :: 3.7
Classifier: Programming Language :: Python :: 3.8
Classifier: Programming Language :: Python :: 3.9
Requires-Dist: pydantic (>=1.9.0,<2.0.0)
Project-URL: Repository, https://github.com/SecurityRiskAdvisors/py-attire-schema
